README.md
setup.py
devicebit/__init__.py
devicebit/device.py
devicebit.egg-info/PKG-INFO
devicebit.egg-info/SOURCES.txt
devicebit.egg-info/dependency_links.txt
devicebit.egg-info/top_level.txt