Metadata-Version: 2.1
Name: devicebit
Version: 0.1.8
Summary: devicebit api for WTH3080,YNM3000
Home-page: https://github.com/
Author: yangbo1979
Author-email: gyangbo@gmail.com
License: UNKNOWN
Platform: UNKNOWN
Classifier: Programming Language :: Python :: 3
Classifier: License :: OSI Approved :: MIT License
Classifier: Operating System :: OS Independent
